globalite/__init__.py
globalite/__main__.py
globalite/connection_manager.py
globalite-0.0.1.dist-info/licenses/LICENSE
tests/__init__.py
tests/context.py
tests/test_globalite.py
globalite-0.0.1.dist-info/METADATA
globalite-0.0.1.dist-info/WHEEL
globalite-0.0.1.dist-info/top_level.txt
globalite-0.0.1.dist-info/RECORD
