Metadata-Version: 2.4
Name: globalite
Version: 0.0.1
Summary: Easy global variables
Author: Bakhoj
Author-email: Bakhoj <anders2108@gmail.com>
Project-URL: Homepage, https://github.com/bakhoj/globalite
Project-URL: Issues, https://github.com/bakhoj/globalite/issues
Classifier: Programming Language :: Python :: 3
Classifier: License :: OSI Approved :: MIT License
Classifier: Operating System :: OS Independent
Requires-Python: >=3.9
License-File: LICENSE
Dynamic: author
Dynamic: license-file
Dynamic: requires-python
